[
    {
        "nom": "jean",
        "prenom": "dujardin",
        "numero_etudiant": "11111111",
        "password": ""
    },
    {
        "nom": "paul",
        "prenom": "mirabel",
        "numero_etudiant": "12345678",
        "password": ""
    },
    {
        "nom": "james",
        "prenom": "bond",
        "numero_etudiant": "11111111",
        "password": ""
    },
    {
        "nom": "mdr",
        "prenom": "mdr",
        "numero_etudiant": "00000000",
        "password": "6dd3c7b5f4742b76e281242fdce9d78da53899fb52d132d63b7544df367fa9005c0a5cc0d5fa74e4986a6327ef343d7f3db5b8ad9675b94ab93d93db0bb3e19c"
    },
    {
        "nom": "b",
        "prenom": "b",
        "numero_etudiant": "22222222",
        "password": "b"
    },
    {
        "nom": "c",
        "prenom": "c",
        "numero_etudiant": "33333333",
        "password": "c"
    },
    {
        "nom": "d",
        "prenom": "d",
        "numero_etudiant": "44444444",
        "password": "d"
    },
    {
        "nom": "e",
        "prenom": "e",
        "numero_etudiant": "55555555",
        "password": "e"
    },
    {
        "nom": "test",
        "prenom": "test",
        "numero_etudiant": "00000000",
        "password": "test"
    },
    {
        "nom": "karylin",
        "prenom": "chandra",
        "numero_etudiant": "86118630",
        "password": "hh"
    },
    {
        "nom": "revkah",
        "prenom": "emma",
        "numero_etudiant": "05078612",
        "password": ""
    },
    {
        "nom": "talia",
        "prenom": "ivett",
        "numero_etudiant": "70375069",
        "password": ""
    },
    {
        "nom": "terencio",
        "prenom": "pollyanna",
        "numero_etudiant": "95103880",
        "password": ""
    },
    {
        "nom": "guildroy",
        "prenom": "sharlene",
        "numero_etudiant": "46838149",
        "password": ""
    },
    {
        "nom": "dimitris",
        "prenom": "pierette",
        "numero_etudiant": "85533982",
        "password": ""
    },
    {
        "nom": "vorster",
        "prenom": "tybie",
        "numero_etudiant": "03752599",
        "password": ""
    },
    {
        "nom": "penelopa",
        "prenom": "hermione",
        "numero_etudiant": "52426426",
        "password": ""
    },
    {
        "nom": "brenn",
        "prenom": "jaclyn",
        "numero_etudiant": "40100553",
        "password": ""
    },
    {
        "nom": "bobbee",
        "prenom": "emelina",
        "numero_etudiant": "49917505",
        "password": ""
    },
    {
        "nom": "destinee",
        "prenom": "ann-marie",
        "numero_etudiant": "00236489",
        "password": ""
    },
    {
        "nom": "rillings",
        "prenom": "yolane",
        "numero_etudiant": "03359980",
        "password": ""
    },
    {
        "nom": "munn",
        "prenom": "luci",
        "numero_etudiant": "11972569",
        "password": ""
    },
    {
        "nom": "vary",
        "prenom": "ebonee",
        "numero_etudiant": "83878321",
        "password": ""
    },
    {
        "nom": "callista",
        "prenom": "darlleen",
        "numero_etudiant": "25389679",
        "password": ""
    },
    {
        "nom": "odysseus",
        "prenom": "elsie",
        "numero_etudiant": "14488818",
        "password": ""
    },
    {
        "nom": "phyllis",
        "prenom": "misha",
        "numero_etudiant": "42213249",
        "password": ""
    },
    {
        "nom": "boycey",
        "prenom": "veda",
        "numero_etudiant": "93052908",
        "password": ""
    },
    {
        "nom": "milde",
        "prenom": "hannis",
        "numero_etudiant": "54301992",
        "password": ""
    },
    {
        "nom": "othilia",
        "prenom": "willetta",
        "numero_etudiant": "37097781",
        "password": ""
    },
    {
        "nom": "cleavland",
        "prenom": "rebeca",
        "numero_etudiant": "52275201",
        "password": ""
    },
    {
        "nom": "margarete",
        "prenom": "hallie",
        "numero_etudiant": "35810154",
        "password": ""
    },
    {
        "nom": "bergman",
        "prenom": "harrietta",
        "numero_etudiant": "54952016",
        "password": ""
    },
    {
        "nom": "secrest",
        "prenom": "gabi",
        "numero_etudiant": "41332290",
        "password": ""
    },
    {
        "nom": "lamoree",
        "prenom": "candy",
        "numero_etudiant": "60851267",
        "password": ""
    },
    {
        "nom": "anestassia",
        "prenom": "ermengarde",
        "numero_etudiant": "20790067",
        "password": ""
    },
    {
        "nom": "loeb",
        "prenom": "tera",
        "numero_etudiant": "67566461",
        "password": ""
    },
    {
        "nom": "toffic",
        "prenom": "janey",
        "numero_etudiant": "50954437",
        "password": ""
    },
    {
        "nom": "willie",
        "prenom": "gusella",
        "numero_etudiant": "02162588",
        "password": ""
    },
    {
        "nom": "saree",
        "prenom": "trudie",
        "numero_etudiant": "66929726",
        "password": ""
    },
    {
        "nom": "soneson",
        "prenom": "karolina",
        "numero_etudiant": "68822536",
        "password": ""
    },
    {
        "nom": "levey",
        "prenom": "regina",
        "numero_etudiant": "30358272",
        "password": ""
    },
    {
        "nom": "graig",
        "prenom": "basia",
        "numero_etudiant": "60320381",
        "password": ""
    },
    {
        "nom": "greyson",
        "prenom": "elvira",
        "numero_etudiant": "94018991",
        "password": ""
    },
    {
        "nom": "amethist",
        "prenom": "penelopa",
        "numero_etudiant": "17526627",
        "password": ""
    },
    {
        "nom": "vanni",
        "prenom": "arlena",
        "numero_etudiant": "99839012",
        "password": ""
    },
    {
        "nom": "juan",
        "prenom": "charmaine",
        "numero_etudiant": "08016153",
        "password": ""
    },
    {
        "nom": "uund",
        "prenom": "madalyn",
        "numero_etudiant": "80732065",
        "password": ""
    },
    {
        "nom": "krystle",
        "prenom": "loree",
        "numero_etudiant": "53907533",
        "password": ""
    },
    {
        "nom": "sawtelle",
        "prenom": "fredericka",
        "numero_etudiant": "79911668",
        "password": ""
    },
    {
        "nom": "lorain",
        "prenom": "marnia",
        "numero_etudiant": "92344454",
        "password": ""
    },
    {
        "nom": "cassius",
        "prenom": "bibby",
        "numero_etudiant": "05878261",
        "password": ""
    },
    {
        "nom": "o_rourke",
        "prenom": "zia",
        "numero_etudiant": "92485400",
        "password": ""
    },
    {
        "nom": "calhoun",
        "prenom": "sissy",
        "numero_etudiant": "12377751",
        "password": ""
    },
    {
        "nom": "august",
        "prenom": "eugine",
        "numero_etudiant": "78914398",
        "password": ""
    },
    {
        "nom": "ciro",
        "prenom": "cassondra",
        "numero_etudiant": "61198387",
        "password": ""
    },
    {
        "nom": "holbrook",
        "prenom": "fred",
        "numero_etudiant": "67708429",
        "password": ""
    },
    {
        "nom": "ummersen",
        "prenom": "genevra",
        "numero_etudiant": "73456006",
        "password": ""
    },
    {
        "nom": "moina",
        "prenom": "jere",
        "numero_etudiant": "16615154",
        "password": ""
    },
    {
        "nom": "haymes",
        "prenom": "ida",
        "numero_etudiant": "85313378",
        "password": ""
    },
    {
        "nom": "zuzana",
        "prenom": "lolita",
        "numero_etudiant": "79347411",
        "password": ""
    },
    {
        "nom": "denis",
        "prenom": "georgetta",
        "numero_etudiant": "66194073",
        "password": ""
    },
    {
        "nom": "eno",
        "prenom": "viviene",
        "numero_etudiant": "64612889",
        "password": ""
    },
    {
        "nom": "huggins",
        "prenom": "jsandye",
        "numero_etudiant": "43664286",
        "password": ""
    },
    {
        "nom": "iaverne",
        "prenom": "ebonee",
        "numero_etudiant": "96116198",
        "password": ""
    },
    {
        "nom": "pozzy",
        "prenom": "elka",
        "numero_etudiant": "35358175",
        "password": ""
    },
    {
        "nom": "anis",
        "prenom": "gusella",
        "numero_etudiant": "55948754",
        "password": ""
    },
    {
        "nom": "mclaughlin",
        "prenom": "kathy",
        "numero_etudiant": "72013363",
        "password": ""
    },
    {
        "nom": "stanwood",
        "prenom": "audrie",
        "numero_etudiant": "49767016",
        "password": ""
    },
    {
        "nom": "christine",
        "prenom": "lynea",
        "numero_etudiant": "68505016",
        "password": ""
    },
    {
        "nom": "winthorpe",
        "prenom": "cherrita",
        "numero_etudiant": "44409796",
        "password": ""
    },
    {
        "nom": "alisia",
        "prenom": "theodora",
        "numero_etudiant": "58307633",
        "password": ""
    },
    {
        "nom": "klemperer",
        "prenom": "bobinette",
        "numero_etudiant": "71091600",
        "password": ""
    },
    {
        "nom": "rubie",
        "prenom": "augustine",
        "numero_etudiant": "23628304",
        "password": ""
    },
    {
        "nom": "glenden",
        "prenom": "helsa",
        "numero_etudiant": "23796145",
        "password": ""
    },
    {
        "nom": "vanni",
        "prenom": "roberta",
        "numero_etudiant": "83064767",
        "password": ""
    },
    {
        "nom": "winnick",
        "prenom": "bernie",
        "numero_etudiant": "02677386",
        "password": ""
    },
    {
        "nom": "publia",
        "prenom": "mady",
        "numero_etudiant": "67076818",
        "password": ""
    },
    {
        "nom": "adamsen",
        "prenom": "malina",
        "numero_etudiant": "62444830",
        "password": ""
    },
    {
        "nom": "leifeste",
        "prenom": "clementine",
        "numero_etudiant": "82834417",
        "password": ""
    },
    {
        "nom": "rogerio",
        "prenom": "rani",
        "numero_etudiant": "36996851",
        "password": ""
    },
    {
        "nom": "harl",
        "prenom": "basia",
        "numero_etudiant": "56721107",
        "password": ""
    },
    {
        "nom": "hortensia",
        "prenom": "teriann",
        "numero_etudiant": "14299387",
        "password": ""
    },
    {
        "nom": "greenwald",
        "prenom": "briney",
        "numero_etudiant": "52603074",
        "password": ""
    },
    {
        "nom": "kenwood",
        "prenom": "florie",
        "numero_etudiant": "27810379",
        "password": ""
    },
    {
        "nom": "vins",
        "prenom": "frank",
        "numero_etudiant": "80389084",
        "password": ""
    },
    {
        "nom": "sparhawk",
        "prenom": "modestia",
        "numero_etudiant": "95694353",
        "password": ""
    },
    {
        "nom": "gabrielli",
        "prenom": "clementine",
        "numero_etudiant": "75774246",
        "password": ""
    },
    {
        "nom": "slifka",
        "prenom": "aubrie",
        "numero_etudiant": "21949232",
        "password": ""
    },
    {
        "nom": "lorain",
        "prenom": "susan",
        "numero_etudiant": "71254455",
        "password": ""
    },
    {
        "nom": "franza",
        "prenom": "alie",
        "numero_etudiant": "67627353",
        "password": ""
    },
    {
        "nom": "libna",
        "prenom": "linzy",
        "numero_etudiant": "71860573",
        "password": ""
    },
    {
        "nom": "alcott",
        "prenom": "oralee",
        "numero_etudiant": "43413639",
        "password": ""
    },
    {
        "nom": "rillings",
        "prenom": "janeczka",
        "numero_etudiant": "34485869",
        "password": ""
    },
    {
        "nom": "nisbet",
        "prenom": "claudina",
        "numero_etudiant": "41350100",
        "password": ""
    },
    {
        "nom": "barney",
        "prenom": "korrie",
        "numero_etudiant": "95856487",
        "password": ""
    },
    {
        "nom": "drus",
        "prenom": "tani",
        "numero_etudiant": "07492727",
        "password": ""
    },
    {
        "nom": "holtz",
        "prenom": "letizia",
        "numero_etudiant": "27249797",
        "password": ""
    },
    {
        "nom": "zina",
        "prenom": "barbara",
        "numero_etudiant": "94102070",
        "password": ""
    },
    {
        "nom": "schonfeld",
        "prenom": "mathilda",
        "numero_etudiant": "41084567",
        "password": ""
    },
    {
        "nom": "yuille",
        "prenom": "ericka",
        "numero_etudiant": "96000831",
        "password": ""
    },
    {
        "nom": "giff",
        "prenom": "fanchon",
        "numero_etudiant": "31069846",
        "password": ""
    },
    {
        "nom": "morgun",
        "prenom": "coral",
        "numero_etudiant": "46322512",
        "password": ""
    },
    {
        "nom": "travax",
        "prenom": "corly",
        "numero_etudiant": "71538710",
        "password": ""
    },
    {
        "nom": "ader",
        "prenom": "emmey",
        "numero_etudiant": "94448818",
        "password": ""
    },
    {
        "nom": "alejoa",
        "prenom": "kylynn",
        "numero_etudiant": "49992001",
        "password": ""
    },
    {
        "nom": "ludewig",
        "prenom": "arabel",
        "numero_etudiant": "10680242",
        "password": ""
    },
    {
        "nom": "mathilde",
        "prenom": "tonia",
        "numero_etudiant": "59170898",
        "password": ""
    },
    {
        "nom": "anton",
        "prenom": "randa",
        "numero_etudiant": "30137777",
        "password": ""
    },
    {
        "nom": "gherardo",
        "prenom": "tomasina",
        "numero_etudiant": "58985452",
        "password": ""
    },
    {
        "nom": "ardeha",
        "prenom": "gale",
        "numero_etudiant": "32817728",
        "password": ""
    },
    {
        "nom": "morehouse",
        "prenom": "grier",
        "numero_etudiant": "28836785",
        "password": ""
    },
    {
        "nom": "bennie",
        "prenom": "genovera",
        "numero_etudiant": "49111398",
        "password": ""
    },
    {
        "nom": "muriel",
        "prenom": "chickie",
        "numero_etudiant": "46470833",
        "password": ""
    },
    {
        "nom": "marijo",
        "prenom": "deloria",
        "numero_etudiant": "84574791",
        "password": ""
    },
    {
        "nom": "jacqui",
        "prenom": "rebeca",
        "numero_etudiant": "14097370",
        "password": ""
    },
    {
        "nom": "salchunas",
        "prenom": "luci",
        "numero_etudiant": "88951167",
        "password": ""
    },
    {
        "nom": "miru",
        "prenom": "vivia",
        "numero_etudiant": "79051972",
        "password": ""
    },
    {
        "nom": "lilas",
        "prenom": "alie",
        "numero_etudiant": "64917900",
        "password": ""
    },
    {
        "nom": "tippets",
        "prenom": "ana",
        "numero_etudiant": "26744969",
        "password": ""
    },
    {
        "nom": "tyson",
        "prenom": "alyssa",
        "numero_etudiant": "63647270",
        "password": ""
    },
    {
        "nom": "christine",
        "prenom": "randa",
        "numero_etudiant": "01857033",
        "password": ""
    },
    {
        "nom": "kaja",
        "prenom": "agathe",
        "numero_etudiant": "22739444",
        "password": ""
    },
    {
        "nom": "ludewig",
        "prenom": "tamqrah",
        "numero_etudiant": "52129778",
        "password": ""
    },
    {
        "nom": "stav",
        "prenom": "lolita",
        "numero_etudiant": "07041651",
        "password": ""
    },
    {
        "nom": "ummersen",
        "prenom": "judy",
        "numero_etudiant": "34087696",
        "password": ""
    },
    {
        "nom": "arne",
        "prenom": "cyndie",
        "numero_etudiant": "46901194",
        "password": ""
    },
    {
        "nom": "bobbee",
        "prenom": "myriam",
        "numero_etudiant": "58874607",
        "password": ""
    },
    {
        "nom": "shanley",
        "prenom": "brianna",
        "numero_etudiant": "96158047",
        "password": ""
    },
    {
        "nom": "dermott",
        "prenom": "violet",
        "numero_etudiant": "83292675",
        "password": ""
    },
    {
        "nom": "waite",
        "prenom": "lisette",
        "numero_etudiant": "56045046",
        "password": ""
    },
    {
        "nom": "darrell",
        "prenom": "daune",
        "numero_etudiant": "84834476",
        "password": ""
    },
    {
        "nom": "melleta",
        "prenom": "korrie",
        "numero_etudiant": "09063009",
        "password": ""
    },
    {
        "nom": "kylander",
        "prenom": "leeanne",
        "numero_etudiant": "86675722",
        "password": ""
    },
    {
        "nom": "douglass",
        "prenom": "jessamyn",
        "numero_etudiant": "76031676",
        "password": ""
    },
    {
        "nom": "hewitt",
        "prenom": "carmela",
        "numero_etudiant": "79228685",
        "password": ""
    },
    {
        "nom": "chrystel",
        "prenom": "sonni",
        "numero_etudiant": "39221278",
        "password": ""
    },
    {
        "nom": "neils",
        "prenom": "katharina",
        "numero_etudiant": "95110432",
        "password": ""
    },
    {
        "nom": "zachary",
        "prenom": "catrina",
        "numero_etudiant": "70510900",
        "password": ""
    },
    {
        "nom": "sundin",
        "prenom": "blinni",
        "numero_etudiant": "60516216",
        "password": ""
    },
    {
        "nom": "prober",
        "prenom": "belva",
        "numero_etudiant": "61802803",
        "password": ""
    },
    {
        "nom": "bari",
        "prenom": "beth",
        "numero_etudiant": "04667294",
        "password": ""
    },
    {
        "nom": "guthrie",
        "prenom": "lynde",
        "numero_etudiant": "29221401",
        "password": ""
    },
    {
        "nom": "mintz",
        "prenom": "rhea",
        "numero_etudiant": "85402886",
        "password": ""
    },
    {
        "nom": "lesley",
        "prenom": "ileana",
        "numero_etudiant": "65035212",
        "password": ""
    },
    {
        "nom": "nahum",
        "prenom": "tersina",
        "numero_etudiant": "25090753",
        "password": ""
    },
    {
        "nom": "ehrman",
        "prenom": "estell",
        "numero_etudiant": "04360622",
        "password": ""
    },
    {
        "nom": "constancy",
        "prenom": "lulita",
        "numero_etudiant": "21923068",
        "password": ""
    },
    {
        "nom": "cottle",
        "prenom": "jany",
        "numero_etudiant": "67911938",
        "password": ""
    },
    {
        "nom": "schenck",
        "prenom": "kirstin",
        "numero_etudiant": "49842857",
        "password": ""
    },
    {
        "nom": "narton",
        "prenom": "maryellen",
        "numero_etudiant": "69529885",
        "password": ""
    },
    {
        "nom": "bashemeth",
        "prenom": "olivette",
        "numero_etudiant": "67543243",
        "password": ""
    },
    {
        "nom": "percy",
        "prenom": "bertine",
        "numero_etudiant": "71620957",
        "password": ""
    },
    {
        "nom": "ovid",
        "prenom": "ezmeralda",
        "numero_etudiant": "73244480",
        "password": ""
    },
    {
        "nom": "frodi",
        "prenom": "ruthe",
        "numero_etudiant": "53016218",
        "password": ""
    },
    {
        "nom": "jehu",
        "prenom": "daune",
        "numero_etudiant": "90465877",
        "password": ""
    },
    {
        "nom": "swanhildas",
        "prenom": "cherrita",
        "numero_etudiant": "33838827",
        "password": ""
    },
    {
        "nom": "bennie",
        "prenom": "ashlee",
        "numero_etudiant": "80555513",
        "password": ""
    },
    {
        "nom": "niccolo",
        "prenom": "merle",
        "numero_etudiant": "44665847",
        "password": ""
    },
    {
        "nom": "zetta",
        "prenom": "sheelagh",
        "numero_etudiant": "47728795",
        "password": ""
    },
    {
        "nom": "f",
        "prenom": "f",
        "numero_etudiant": "66666666",
        "password": "f"
    },
    {
        "nom": "g",
        "prenom": "g",
        "numero_etudiant": "77777777",
        "password": "g"
    },
    {
        "nom": "h",
        "prenom": "h",
        "numero_etudiant": "88888888",
        "password": "h"
    },
    {
        "nom": "i",
        "prenom": "i",
        "numero_etudiant": "99999999",
        "password": "i"
    },
    {
        "nom": "j",
        "prenom": "j",
        "numero_etudiant": "10101010",
        "password": "j"
    },
    {
        "nom": "k",
        "prenom": "k",
        "numero_etudiant": "12121212",
        "password": "k"
    },
    {
        "nom": "l",
        "prenom": "l",
        "numero_etudiant": "13131313",
        "password": "l"
    },
    {
        "nom": "m",
        "prenom": "m",
        "numero_etudiant": "14141414",
        "password": "m"
    },
    {
        "nom": "n",
        "prenom": "n",
        "numero_etudiant": "15151515",
        "password": "n"
    },
    {
        "nom": "o",
        "prenom": "o",
        "numero_etudiant": "16161616",
        "password": "o"
    },
    {
        "nom": "p",
        "prenom": "p",
        "numero_etudiant": "17171717",
        "password": "p"
    },
    {
        "nom": "q",
        "prenom": "q",
        "numero_etudiant": "18181818",
        "password": "q"
    },
    {
        "nom": "r",
        "prenom": "r",
        "numero_etudiant": "19191919",
        "password": "r"
    },
    {
        "nom": "s",
        "prenom": "s",
        "numero_etudiant": "20202020",
        "password": "s"
    },
    {
        "nom": "t",
        "prenom": "t",
        "numero_etudiant": "21212121",
        "password": "t"
    },
    {
        "nom": "v",
        "prenom": "v",
        "numero_etudiant": "23232323",
        "password": "v"
    },
    {
        "nom": "w",
        "prenom": "w",
        "numero_etudiant": "24242424",
        "password": "w"
    },
    {
        "nom": "x",
        "prenom": "x",
        "numero_etudiant": "25252525",
        "password": "x"
    },
    {
        "nom": "y",
        "prenom": "y",
        "numero_etudiant": "26262626",
        "password": "y"
    },
    {
        "nom": "z",
        "prenom": "z",
        "numero_etudiant": "27272727",
        "password": "z"
    }
]